setup.cfg
setup.py
rova_client/Rova.py
rova_client/__init__.py
rova_client/helpers.py
rova_client/py.typed
rova_client/utils.py
rova_client.egg-info/PKG-INFO
rova_client.egg-info/SOURCES.txt
rova_client.egg-info/dependency_links.txt
rova_client.egg-info/not-zip-safe
rova_client.egg-info/requires.txt
rova_client.egg-info/top_level.txt