Metadata-Version: 2.1
Name: rova-client
Version: 2.2.7
Summary: Event tracking with rova AI
Author-email: sam@rovaai.com
Requires-Dist: clickhouse-connect>=0.7.0
